CHANGES.rst
MANIFEST.in
README.rst
bootstrap.py
buildout.cfg
screenshot1.png
screenshot10.png
screenshot2.png
screenshot3.png
screenshot4.png
screenshot5.png
screenshot6.png
screenshot7.png
screenshot8.png
screenshot9.png
setup.py
rpi/__init__.py
rpi.asthma_files_site.egg-info/PKG-INFO
rpi.asthma_files_site.egg-info/SOURCES.txt
rpi.asthma_files_site.egg-info/dependency_links.txt
rpi.asthma_files_site.egg-info/entry_points.txt
rpi.asthma_files_site.egg-info/namespace_packages.txt
rpi.asthma_files_site.egg-info/requires.txt
rpi.asthma_files_site.egg-info/top_level.txt
rpi.asthma_files_site.egg-info/zip-safe
rpi/asthma_files_site/__init__.py
rpi/asthma_files_site/configure.zcml
rpi/asthma_files_site/tests.py
rpi/asthma_files_site/browser/__init__.py
rpi/asthma_files_site/browser/configure.zcml
rpi/asthma_files_site/browser/zotero_view.pt
rpi/asthma_files_site/browser/zotero_view.py
rpi/asthma_files_site/content/__init__.py
rpi/asthma_files_site/content/annotation_view.pt
rpi/asthma_files_site/content/artifact_view.pt
rpi/asthma_files_site/content/artifact_view.py
rpi/asthma_files_site/content/audio_artifact.py
rpi/asthma_files_site/content/configure.zcml
rpi/asthma_files_site/content/document_artifact.py
rpi/asthma_files_site/content/image_artifact.py
rpi/asthma_files_site/content/question.py
rpi/asthma_files_site/content/video_artifact.py
rpi/asthma_files_site/profiles/default/metadata.xml
rpi/asthma_files_site/profiles/default/registry.xml
rpi/asthma_files_site/profiles/default/types.xml
rpi/asthma_files_site/profiles/default/types/annotation.xml
rpi/asthma_files_site/profiles/default/types/asthma_file.xml
rpi/asthma_files_site/profiles/default/types/audio_artifact.xml
rpi/asthma_files_site/profiles/default/types/collective.cover.content.xml
rpi/asthma_files_site/profiles/default/types/document_artifact.xml
rpi/asthma_files_site/profiles/default/types/image_artifact.xml
rpi/asthma_files_site/profiles/default/types/question.xml
rpi/asthma_files_site/profiles/default/types/response.xml
rpi/asthma_files_site/profiles/default/types/video_artifact.xml
rpi/asthma_files_site/template-overrides/plone.app.layout.viewlets.logo.pt