Metadata-Version: 1.1
Name: rpi.asthma-files-site
Version: 0.0.4
Summary: Asthma Files Site
Home-page: https://github.com/ACLARKNET/rpi.asthma_files_site
Author: Alex Clark
Author-email: aclark@aclark.net
License: GPL
Keywords: Plone
Platform: UNKNOWN
Classifier: Framework :: Plone :: 4.3
Classifier: Programming Language :: Python :: 2.7
